nn_dataflow/__init__.py
nn_dataflow/util.py
nn_dataflow/version.py
nn_dataflow/core/__init__.py
nn_dataflow/core/buf_shr_scheme.py
nn_dataflow/core/cost.py
nn_dataflow/core/data_category_enum.py
nn_dataflow/core/data_dim_loops.py
nn_dataflow/core/data_layout.py
nn_dataflow/core/fmap_range.py
nn_dataflow/core/int_range.py
nn_dataflow/core/inter_layer_pipeline.py
nn_dataflow/core/layer.py
nn_dataflow/core/loop_blocking.py
nn_dataflow/core/loop_blocking_scheme.py
nn_dataflow/core/loop_blocking_solver.py
nn_dataflow/core/loop_enum.py
nn_dataflow/core/map_strategy.py
nn_dataflow/core/mem_hier_enum.py
nn_dataflow/core/nested_loop_desc.py
nn_dataflow/core/network.py
nn_dataflow/core/nn_dataflow.py
nn_dataflow/core/nn_dataflow_scheme.py
nn_dataflow/core/node_region.py
nn_dataflow/core/option.py
nn_dataflow/core/parallel_enum.py
nn_dataflow/core/partition.py
nn_dataflow/core/partition_scheme.py
nn_dataflow/core/phy_dim2.py
nn_dataflow/core/pipeline_segment.py
nn_dataflow/core/pipeline_segment_timing.py
nn_dataflow/core/resource.py
nn_dataflow/core/scheduling.py
nn_dataflow/core/scheduling_constraint.py
nn_dataflow/nns/__init__.py
nn_dataflow/nns/alex_net.py
nn_dataflow/nns/googlenet.py
nn_dataflow/nns/lstm_gnmt.py
nn_dataflow/nns/lstm_phoneme.py
nn_dataflow/nns/lstm_showtell.py
nn_dataflow/nns/mlp_l.py
nn_dataflow/nns/mlp_m.py
nn_dataflow/nns/mlp_s.py
nn_dataflow/nns/resnet152.py
nn_dataflow/nns/resnet50.py
nn_dataflow/nns/vgg19_net.py
nn_dataflow/nns/vgg_net.py
nn_dataflow/nns/zfnet.py
nn_dataflow/tests/__init__.py
nn_dataflow/tests/dataflow_test/__init__.py
nn_dataflow/tests/dataflow_test/test_nn_dataflow.py
nn_dataflow/tests/dataflow_test/test_scheduling.py
nn_dataflow/tests/loop_blocking_test/__init__.py
nn_dataflow/tests/loop_blocking_test/test_loop_blocking.py
nn_dataflow/tests/loop_blocking_test/test_loop_blocking_fixture.py
nn_dataflow/tests/loop_blocking_test/test_loop_blocking_partition.py
nn_dataflow/tests/loop_blocking_test/test_loop_blocking_scheme.py
nn_dataflow-2.1.dist-info/LICENSE
nn_dataflow-2.1.dist-info/METADATA
nn_dataflow-2.1.dist-info/WHEEL
nn_dataflow-2.1.dist-info/entry_points.txt
nn_dataflow-2.1.dist-info/top_level.txt
nn_dataflow-2.1.dist-info/RECORD
