Metadata-Version: 2.1
Name: nn-dataflow
Version: 2.1
Summary: Explore the energy-efficient dataflow scheduling for neural networks.
Home-page: https://github.com/stanford-mast/nn_dataflow
Author: Mingyu Gao
Author-email: mgao12@stanford.edu
License: BSD 3-clause
Keywords: neural-network scheduling dataflow optimizer
Platform: UNKNOWN
Classifier: Development Status :: 3 - Alpha
Classifier: Intended Audience :: Developers
Classifier: Intended Audience :: Science/Research
Classifier: License :: OSI Approved :: BSD License
Classifier: Programming Language :: Python :: 3.6
Classifier: Programming Language :: Python :: 3.7
Classifier: Topic :: Scientific/Engineering :: Artificial Intelligence
Classifier: Topic :: System :: Hardware
Requires-Dist: argparse
Requires-Dist: coverage (>=4)
Requires-Dist: fastcache (>=1)
Requires-Dist: pytest (>=3)
Requires-Dist: pytest-cov (>=2)
Requires-Dist: pytest-xdist (>=1)
Requires-Dist: sympy (>=1)
